LICENSE.mit
MANIFEST.in
README
setup.py
iso8601/__init__.py
iso8601/iso8601.py
iso8601/test_iso8601.py
iso8601plus.egg-info/PKG-INFO
iso8601plus.egg-info/SOURCES.txt
iso8601plus.egg-info/dependency_links.txt
iso8601plus.egg-info/top_level.txt