Metadata-Version: 1.0
Name: iso8601plus
Version: 0.1.6
Summary: Simple module to parse ISO 8601 dates
Home-page: https://github.com/jimklo/pyiso8601plus
Author: Jim Klo
Author-email: jim.klo@sri.com
License: The MIT License (MIT)
Platform: UNKNOWN
